discord_gateway/__init__.py
discord_gateway/api.py
discord_gateway/constants.py
discord_gateway/discord_objects.py
discord_gateway/discord_user.py
discord_gateway/embed.py
discord_gateway/exceptions.py
discord_gateway/gateway.py
discord_gateway/gateway_handler.py
discord_gateway/gatewaybot.py
discord_gateway/guild_objects.py
discord_gateway/presence.py
discord_gateway/request_manager.py
discord_gateway/types.py
discord_gateway/commands/__init__.py
discord_gateway/commands/command.py
discord_gateway/commands/command_context.py
discord_gateway/commands/command_handler.py
yoshaas_gateway-2.0.1.dist-info/LICENSE
yoshaas_gateway-2.0.1.dist-info/METADATA
yoshaas_gateway-2.0.1.dist-info/WHEEL
yoshaas_gateway-2.0.1.dist-info/top_level.txt
yoshaas_gateway-2.0.1.dist-info/RECORD
