Metadata-Version: 2.1
Name: yoshaas-gateway
Version: 2.0.1
Summary: Simple discord gateway library
Home-page: https://github.com/Yoshaa-pog/DiscordGateway
Author: Yoshaa
Author-email: notmyemail@gmail.com
Classifier: Programming Language :: Python :: 3
Classifier: License :: OSI Approved :: MIT License
Classifier: Operating System :: OS Independent
Requires-Python: >=3.8
License-File: LICENSE
